ext_list.py
ext_list/__init__.py
ext_list/base.py
ext_list/dict_operations.py
ext_list/list_operations.py
ext_list/operator_operations.py
ext_list-1.1.1.dist-info/LICENSE
ext_list-1.1.1.dist-info/METADATA
ext_list-1.1.1.dist-info/WHEEL
ext_list-1.1.1.dist-info/top_level.txt
ext_list-1.1.1.dist-info/RECORD
