Metadata-Version: 2.1
Name: ext-list
Version: 1.1.1
Summary: This is a utility library that extends Python's list operations.
Home-page: https://github.com/sk-guritech/ext-list
Author: Sakaguchi Ryo
Author-email: sakaguchi@sk-techfirm.com
Project-URL: Bug Tracker, https://github.com/sk-guritech/ext-list/issues
Keywords: list,comprehension,iterable,code quality
Classifier: Topic :: Software Development :: Libraries :: Python Modules
Classifier: Development Status :: 4 - Beta
Classifier: Intended Audience :: Developers
Classifier: License :: OSI Approved :: MIT License
Classifier: Natural Language :: English
Classifier: Typing :: Typed
Classifier: Programming Language :: Python
Classifier: Programming Language :: Python :: 3
Classifier: Programming Language :: Python :: 3.7
Classifier: Programming Language :: Python :: 3.8
Classifier: Programming Language :: Python :: 3.9
Classifier: Programming Language :: Python :: 3.10
Classifier: Programming Language :: Python :: 3.11
Classifier: Programming Language :: Python :: 3.12
Requires-Python: >=3.7
License-File: LICENSE
Requires-Dist: typing-extensions
